{
	"entries" : 
	[
		{
			"name" : "ABSL_BUILD_TEST_HELPERS",
			"properties" : 
			[
				{
					"name" : "HELPSTRING",
					"value" : "If ON, Abseil will build libraries that you can use to write tests against Abseil code. This option requires that Abseil is configured to use GoogleTest."
				}
			],
			"type" : "BOOL",
			"value" : "OFF"
		},
		{
			"name" : "ABSL_GOOGLETEST_DOWNLOAD_URL",
			"properties" : 
			[
				{
					"name" : "HELPSTRING",
					"value" : "If set, download GoogleTest from this URL"
				}
			],
			"type" : "STRING",
			"value" : ""
		},
		{
			"name" : "ABSL_INTERNAL_AT_LEAST_CXX17",
			"properties" : 
			[
				{
					"name" : "HELPSTRING",
					"value" : "Test ABSL_INTERNAL_AT_LEAST_CXX17"
				}
			],
			"type" : "INTERNAL",
			"value" : "1"
		},
		{
			"name" : "ABSL_INTERNAL_AT_LEAST_CXX20",
			"properties" : 
			[
				{
					"name" : "HELPSTRING",
					"value" : "Test ABSL_INTERNAL_AT_LEAST_CXX20"
				}
			],
			"type" : "INTERNAL",
			"value" : ""
		},
		{
			"name" : "ABSL_LOCAL_GOOGLETEST_DIR",
			"properties" : 
			[
				{
					"name" : "HELPSTRING",
					"value" : "If ABSL_USE_GOOGLETEST_HEAD is OFF and ABSL_GOOGLETEST_URL is not set, specifies the directory of a local GoogleTest checkout."
				}
			],
			"type" : "PATH",
			"value" : "/usr/src/googletest"
		},
		{
			"name" : "ABSL_USE_EXTERNAL_GOOGLETEST",
			"properties" : 
			[
				{
					"name" : "HELPSTRING",
					"value" : "If ON, Abseil will assume that the targets for GoogleTest are already provided by the including project. This makes sense when Abseil is used with add_subdirectory."
				}
			],
			"type" : "BOOL",
			"value" : "OFF"
		},
		{
			"name" : "ABSL_USE_GOOGLETEST_HEAD",
			"properties" : 
			[
				{
					"name" : "HELPSTRING",
					"value" : "If ON, abseil will download HEAD from GoogleTest at config time."
				}
			],
			"type" : "BOOL",
			"value" : "OFF"
		},
		{
			"name" : "BUILD_TESTING",
			"properties" : 
			[
				{
					"name" : "HELPSTRING",
					"value" : "Build the testing tree."
				}
			],
			"type" : "BOOL",
			"value" : "ON"
		},
		{
			"name" : "BZRCOMMAND",
			"properties" : 
			[
				{
					"name" : "ADVANCED",
					"value" : "1"
				},
				{
					"name" : "HELPSTRING",
					"value" : ""
				}
			],
			"type" : "UNINITIALIZED",
			"value" : ""
		},
		{
			"name" : "CMAKE_ADDR2LINE",
			"properties" : 
			[
				{
					"name" : "ADVANCED",
					"value" : "1"
				},
				{
					"name" : "HELPSTRING",
					"value" : "Path to a program."
				}
			],
			"type" : "FILEPATH",
			"value" : "/usr/bin/addr2line"
		},
		{
			"name" : "CMAKE_AR",
			"properties" : 
			[
				{
					"name" : "ADVANCED",
					"value" : "1"
				},
				{
					"name" : "HELPSTRING",
					"value" : "Path to a program."
				}
			],
			"type" : "FILEPATH",
			"value" : "/usr/bin/ar"
		},
		{
			"name" : "CMAKE_BUILD_CMAKEDIR",
			"properties" : 
			[
				{
					"name" : "ADVANCED",
					"value" : "1"
				},
				{
					"name" : "HELPSTRING",
					"value" : "Directory relative to CMAKE_CURRENT_BINARY_DIR for cmake configuration files"
				}
			],
			"type" : "STRING",
			"value" : "/home/aymanelotfi/Documents/millemiglia/build/_deps/protobuf-build/cmake/protobuf"
		},
		{
			"name" : "CMAKE_BUILD_TYPE",
			"properties" : 
			[
				{
					"name" : "HELPSTRING",
					"value" : "No help, variable specified on the command line."
				}
			],
			"type" : "STRING",
			"value" : "Debug"
		},
		{
			"name" : "CMAKE_CACHEFILE_DIR",
			"properties" : 
			[
				{
					"name" : "HELPSTRING",
					"value" : "This is the directory where this CMakeCache.txt was created"
				}
			],
			"type" : "INTERNAL",
			"value" : "/home/aymanelotfi/Documents/millemiglia/build"
		},
		{
			"name" : "CMAKE_CACHE_MAJOR_VERSION",
			"properties" : 
			[
				{
					"name" : "HELPSTRING",
					"value" : "Major version of cmake used to create the current loaded cache"
				}
			],
			"type" : "INTERNAL",
			"value" : "3"
		},
		{
			"name" : "CMAKE_CACHE_MINOR_VERSION",
			"properties" : 
			[
				{
					"name" : "HELPSTRING",
					"value" : "Minor version of cmake used to create the current loaded cache"
				}
			],
			"type" : "INTERNAL",
			"value" : "27"
		},
		{
			"name" : "CMAKE_CACHE_PATCH_VERSION",
			"properties" : 
			[
				{
					"name" : "HELPSTRING",
					"value" : "Patch version of cmake used to create the current loaded cache"
				}
			],
			"type" : "INTERNAL",
			"value" : "9"
		},
		{
			"name" : "CMAKE_COLOR_MAKEFILE",
			"properties" : 
			[
				{
					"name" : "ADVANCED",
					"value" : "1"
				},
				{
					"name" : "HELPSTRING",
					"value" : "Enable/Disable color output during build."
				}
			],
			"type" : "BOOL",
			"value" : "ON"
		},
		{
			"name" : "CMAKE_COMMAND",
			"properties" : 
			[
				{
					"name" : "HELPSTRING",
					"value" : "Path to CMake executable."
				}
			],
			"type" : "INTERNAL",
			"value" : "/usr/bin/cmake"
		},
		{
			"name" : "CMAKE_CPACK_COMMAND",
			"properties" : 
			[
				{
					"name" : "HELPSTRING",
					"value" : "Path to cpack program executable."
				}
			],
			"type" : "INTERNAL",
			"value" : "/usr/bin/cpack"
		},
		{
			"name" : "CMAKE_CTEST_COMMAND",
			"properties" : 
			[
				{
					"name" : "ADVANCED",
					"value" : "1"
				},
				{
					"name" : "HELPSTRING",
					"value" : "Path to ctest program executable."
				}
			],
			"type" : "INTERNAL",
			"value" : "/usr/bin/ctest"
		},
		{
			"name" : "CMAKE_CXX_COMPILER",
			"properties" : 
			[
				{
					"name" : "ADVANCED",
					"value" : "1"
				},
				{
					"name" : "HELPSTRING",
					"value" : "No help, variable specified on the command line."
				}
			],
			"type" : "FILEPATH",
			"value" : "/usr/bin/g++"
		},
		{
			"name" : "CMAKE_CXX_COMPILER_AR",
			"properties" : 
			[
				{
					"name" : "ADVANCED",
					"value" : "1"
				},
				{
					"name" : "HELPSTRING",
					"value" : "A wrapper around 'ar' adding the appropriate '--plugin' option for the GCC compiler"
				}
			],
			"type" : "FILEPATH",
			"value" : "/usr/bin/gcc-ar-13"
		},
		{
			"name" : "CMAKE_CXX_COMPILER_RANLIB",
			"properties" : 
			[
				{
					"name" : "ADVANCED",
					"value" : "1"
				},
				{
					"name" : "HELPSTRING",
					"value" : "A wrapper around 'ranlib' adding the appropriate '--plugin' option for the GCC compiler"
				}
			],
			"type" : "FILEPATH",
			"value" : "/usr/bin/gcc-ranlib-13"
		},
		{
			"name" : "CMAKE_CXX_FLAGS",
			"properties" : 
			[
				{
					"name" : "ADVANCED",
					"value" : "1"
				},
				{
					"name" : "HELPSTRING",
					"value" : "Flags used by the CXX compiler during all build types."
				}
			],
			"type" : "STRING",
			"value" : ""
		},
		{
			"name" : "CMAKE_CXX_FLAGS_DEBUG",
			"properties" : 
			[
				{
					"name" : "ADVANCED",
					"value" : "1"
				},
				{
					"name" : "HELPSTRING",
					"value" : "Flags used by the CXX compiler during DEBUG builds."
				}
			],
			"type" : "STRING",
			"value" : "-g"
		},
		{
			"name" : "CMAKE_CXX_FLAGS_MINSIZEREL",
			"properties" : 
			[
				{
					"name" : "ADVANCED",
					"value" : "1"
				},
				{
					"name" : "HELPSTRING",
					"value" : "Flags used by the CXX compiler during MINSIZEREL builds."
				}
			],
			"type" : "STRING",
			"value" : "-Os -DNDEBUG"
		},
		{
			"name" : "CMAKE_CXX_FLAGS_RELEASE",
			"properties" : 
			[
				{
					"name" : "ADVANCED",
					"value" : "1"
				},
				{
					"name" : "HELPSTRING",
					"value" : "Flags used by the CXX compiler during RELEASE builds."
				}
			],
			"type" : "STRING",
			"value" : "-O3 -DNDEBUG"
		},
		{
			"name" : "CMAKE_CXX_FLAGS_RELWITHDEBINFO",
			"properties" : 
			[
				{
					"name" : "ADVANCED",
					"value" : "1"
				},
				{
					"name" : "HELPSTRING",
					"value" : "Flags used by the CXX compiler during RELWITHDEBINFO builds."
				}
			],
			"type" : "STRING",
			"value" : "-O2 -g -DNDEBUG"
		},
		{
			"name" : "CMAKE_C_COMPILER",
			"properties" : 
			[
				{
					"name" : "ADVANCED",
					"value" : "1"
				},
				{
					"name" : "HELPSTRING",
					"value" : "No help, variable specified on the command line."
				}
			],
			"type" : "FILEPATH",
			"value" : "/usr/bin/gcc"
		},
		{
			"name" : "CMAKE_C_COMPILER_AR",
			"properties" : 
			[
				{
					"name" : "ADVANCED",
					"value" : "1"
				},
				{
					"name" : "HELPSTRING",
					"value" : "A wrapper around 'ar' adding the appropriate '--plugin' option for the GCC compiler"
				}
			],
			"type" : "FILEPATH",
			"value" : "/usr/bin/gcc-ar-13"
		},
		{
			"name" : "CMAKE_C_COMPILER_RANLIB",
			"properties" : 
			[
				{
					"name" : "ADVANCED",
					"value" : "1"
				},
				{
					"name" : "HELPSTRING",
					"value" : "A wrapper around 'ranlib' adding the appropriate '--plugin' option for the GCC compiler"
				}
			],
			"type" : "FILEPATH",
			"value" : "/usr/bin/gcc-ranlib-13"
		},
		{
			"name" : "CMAKE_C_FLAGS",
			"properties" : 
			[
				{
					"name" : "ADVANCED",
					"value" : "1"
				},
				{
					"name" : "HELPSTRING",
					"value" : "Flags used by the C compiler during all build types."
				}
			],
			"type" : "STRING",
			"value" : ""
		},
		{
			"name" : "CMAKE_C_FLAGS_DEBUG",
			"properties" : 
			[
				{
					"name" : "ADVANCED",
					"value" : "1"
				},
				{
					"name" : "HELPSTRING",
					"value" : "Flags used by the C compiler during DEBUG builds."
				}
			],
			"type" : "STRING",
			"value" : "-g"
		},
		{
			"name" : "CMAKE_C_FLAGS_MINSIZEREL",
			"properties" : 
			[
				{
					"name" : "ADVANCED",
					"value" : "1"
				},
				{
					"name" : "HELPSTRING",
					"value" : "Flags used by the C compiler during MINSIZEREL builds."
				}
			],
			"type" : "STRING",
			"value" : "-Os -DNDEBUG"
		},
		{
			"name" : "CMAKE_C_FLAGS_RELEASE",
			"properties" : 
			[
				{
					"name" : "ADVANCED",
					"value" : "1"
				},
				{
					"name" : "HELPSTRING",
					"value" : "Flags used by the C compiler during RELEASE builds."
				}
			],
			"type" : "STRING",
			"value" : "-O3 -DNDEBUG"
		},
		{
			"name" : "CMAKE_C_FLAGS_RELWITHDEBINFO",
			"properties" : 
			[
				{
					"name" : "ADVANCED",
					"value" : "1"
				},
				{
					"name" : "HELPSTRING",
					"value" : "Flags used by the C compiler during RELWITHDEBINFO builds."
				}
			],
			"type" : "STRING",
			"value" : "-O2 -g -DNDEBUG"
		},
		{
			"name" : "CMAKE_DLLTOOL",
			"properties" : 
			[
				{
					"name" : "ADVANCED",
					"value" : "1"
				},
				{
					"name" : "HELPSTRING",
					"value" : "Path to a program."
				}
			],
			"type" : "FILEPATH",
			"value" : "CMAKE_DLLTOOL-NOTFOUND"
		},
		{
			"name" : "CMAKE_EXECUTABLE_FORMAT",
			"properties" : 
			[
				{
					"name" : "HELPSTRING",
					"value" : "Executable file format"
				}
			],
			"type" : "INTERNAL",
			"value" : "ELF"
		},
		{
			"name" : "CMAKE_EXE_LINKER_FLAGS",
			"properties" : 
			[
				{
					"name" : "ADVANCED",
					"value" : "1"
				},
				{
					"name" : "HELPSTRING",
					"value" : "Flags used by the linker during all build types."
				}
			],
			"type" : "STRING",
			"value" : ""
		},
		{
			"name" : "CMAKE_EXE_LINKER_FLAGS_DEBUG",
			"properties" : 
			[
				{
					"name" : "ADVANCED",
					"value" : "1"
				},
				{
					"name" : "HELPSTRING",
					"value" : "Flags used by the linker during DEBUG builds."
				}
			],
			"type" : "STRING",
			"value" : ""
		},
		{
			"name" : "CMAKE_EXE_LINKER_FLAGS_MINSIZEREL",
			"properties" : 
			[
				{
					"name" : "ADVANCED",
					"value" : "1"
				},
				{
					"name" : "HELPSTRING",
					"value" : "Flags used by the linker during MINSIZEREL builds."
				}
			],
			"type" : "STRING",
			"value" : ""
		},
		{
			"name" : "CMAKE_EXE_LINKER_FLAGS_RELEASE",
			"properties" : 
			[
				{
					"name" : "ADVANCED",
					"value" : "1"
				},
				{
					"name" : "HELPSTRING",
					"value" : "Flags used by the linker during RELEASE builds."
				}
			],
			"type" : "STRING",
			"value" : ""
		},
		{
			"name" : "CMAKE_EXE_LINKER_FLAGS_RELWITHDEBINFO",
			"properties" : 
			[
				{
					"name" : "ADVANCED",
					"value" : "1"
				},
				{
					"name" : "HELPSTRING",
					"value" : "Flags used by the linker during RELWITHDEBINFO builds."
				}
			],
			"type" : "STRING",
			"value" : ""
		},
		{
			"name" : "CMAKE_EXPORT_COMPILE_COMMANDS",
			"properties" : 
			[
				{
					"name" : "ADVANCED",
					"value" : "1"
				},
				{
					"name" : "HELPSTRING",
					"value" : "No help, variable specified on the command line."
				}
			],
			"type" : "BOOL",
			"value" : "TRUE"
		},
		{
			"name" : "CMAKE_EXTRA_GENERATOR",
			"properties" : 
			[
				{
					"name" : "HELPSTRING",
					"value" : "Name of external makefile project generator."
				}
			],
			"type" : "INTERNAL",
			"value" : ""
		},
		{
			"name" : "CMAKE_FIND_PACKAGE_REDIRECTS_DIR",
			"properties" : 
			[
				{
					"name" : "HELPSTRING",
					"value" : "Value Computed by CMake."
				}
			],
			"type" : "STATIC",
			"value" : "/home/aymanelotfi/Documents/millemiglia/build/CMakeFiles/pkgRedirects"
		},
		{
			"name" : "CMAKE_GENERATOR",
			"properties" : 
			[
				{
					"name" : "HELPSTRING",
					"value" : "Name of generator."
				}
			],
			"type" : "INTERNAL",
			"value" : "Unix Makefiles"
		},
		{
			"name" : "CMAKE_GENERATOR_INSTANCE",
			"properties" : 
			[
				{
					"name" : "HELPSTRING",
					"value" : "Generator instance identifier."
				}
			],
			"type" : "INTERNAL",
			"value" : ""
		},
		{
			"name" : "CMAKE_GENERATOR_PLATFORM",
			"properties" : 
			[
				{
					"name" : "HELPSTRING",
					"value" : "Name of generator platform."
				}
			],
			"type" : "INTERNAL",
			"value" : ""
		},
		{
			"name" : "CMAKE_GENERATOR_TOOLSET",
			"properties" : 
			[
				{
					"name" : "HELPSTRING",
					"value" : "Name of generator toolset."
				}
			],
			"type" : "INTERNAL",
			"value" : ""
		},
		{
			"name" : "CMAKE_HAVE_LIBC_PTHREAD",
			"properties" : 
			[
				{
					"name" : "HELPSTRING",
					"value" : "Test CMAKE_HAVE_LIBC_PTHREAD"
				}
			],
			"type" : "INTERNAL",
			"value" : "1"
		},
		{
			"name" : "CMAKE_HOME_DIRECTORY",
			"properties" : 
			[
				{
					"name" : "HELPSTRING",
					"value" : "Source directory with the top level CMakeLists.txt file for this project"
				}
			],
			"type" : "INTERNAL",
			"value" : "/home/aymanelotfi/Documents/millemiglia"
		},
		{
			"name" : "CMAKE_INSTALL_BINDIR",
			"properties" : 
			[
				{
					"name" : "ADVANCED",
					"value" : "1"
				},
				{
					"name" : "HELPSTRING",
					"value" : "User executables (bin)"
				}
			],
			"type" : "PATH",
			"value" : "bin"
		},
		{
			"name" : "CMAKE_INSTALL_CMAKEDIR",
			"properties" : 
			[
				{
					"name" : "ADVANCED",
					"value" : "1"
				},
				{
					"name" : "HELPSTRING",
					"value" : "Directory relative to CMAKE_INSTALL to install the cmake configuration files"
				}
			],
			"type" : "STRING",
			"value" : "lib/cmake/protobuf"
		},
		{
			"name" : "CMAKE_INSTALL_DATADIR",
			"properties" : 
			[
				{
					"name" : "ADVANCED",
					"value" : "1"
				},
				{
					"name" : "HELPSTRING",
					"value" : "Read-only architecture-independent data (DATAROOTDIR)"
				}
			],
			"type" : "PATH",
			"value" : ""
		},
		{
			"name" : "CMAKE_INSTALL_DATAROOTDIR",
			"properties" : 
			[
				{
					"name" : "ADVANCED",
					"value" : "1"
				},
				{
					"name" : "HELPSTRING",
					"value" : "Read-only architecture-independent data root (share)"
				}
			],
			"type" : "PATH",
			"value" : "share"
		},
		{
			"name" : "CMAKE_INSTALL_DOCDIR",
			"properties" : 
			[
				{
					"name" : "ADVANCED",
					"value" : "1"
				},
				{
					"name" : "HELPSTRING",
					"value" : "Documentation root (DATAROOTDIR/doc/PROJECT_NAME)"
				}
			],
			"type" : "PATH",
			"value" : ""
		},
		{
			"name" : "CMAKE_INSTALL_EXAMPLEDIR",
			"properties" : 
			[
				{
					"name" : "ADVANCED",
					"value" : "1"
				},
				{
					"name" : "HELPSTRING",
					"value" : "Directory relative to CMAKE_INSTALL_DATA to install examples"
				}
			],
			"type" : "STRING",
			"value" : "share/protobuf/examples"
		},
		{
			"name" : "CMAKE_INSTALL_INCLUDEDIR",
			"properties" : 
			[
				{
					"name" : "ADVANCED",
					"value" : "1"
				},
				{
					"name" : "HELPSTRING",
					"value" : "C header files (include)"
				}
			],
			"type" : "PATH",
			"value" : "include"
		},
		{
			"name" : "CMAKE_INSTALL_INFODIR",
			"properties" : 
			[
				{
					"name" : "ADVANCED",
					"value" : "1"
				},
				{
					"name" : "HELPSTRING",
					"value" : "Info documentation (DATAROOTDIR/info)"
				}
			],
			"type" : "PATH",
			"value" : ""
		},
		{
			"name" : "CMAKE_INSTALL_LIBDIR",
			"properties" : 
			[
				{
					"name" : "ADVANCED",
					"value" : "1"
				},
				{
					"name" : "HELPSTRING",
					"value" : "Object code libraries (lib)"
				}
			],
			"type" : "PATH",
			"value" : "lib"
		},
		{
			"name" : "CMAKE_INSTALL_LIBEXECDIR",
			"properties" : 
			[
				{
					"name" : "ADVANCED",
					"value" : "1"
				},
				{
					"name" : "HELPSTRING",
					"value" : "Program executables (libexec)"
				}
			],
			"type" : "PATH",
			"value" : "libexec"
		},
		{
			"name" : "CMAKE_INSTALL_LOCALEDIR",
			"properties" : 
			[
				{
					"name" : "ADVANCED",
					"value" : "1"
				},
				{
					"name" : "HELPSTRING",
					"value" : "Locale-dependent data (DATAROOTDIR/locale)"
				}
			],
			"type" : "PATH",
			"value" : ""
		},
		{
			"name" : "CMAKE_INSTALL_LOCALSTATEDIR",
			"properties" : 
			[
				{
					"name" : "ADVANCED",
					"value" : "1"
				},
				{
					"name" : "HELPSTRING",
					"value" : "Modifiable single-machine data (var)"
				}
			],
			"type" : "PATH",
			"value" : "var"
		},
		{
			"name" : "CMAKE_INSTALL_MANDIR",
			"properties" : 
			[
				{
					"name" : "ADVANCED",
					"value" : "1"
				},
				{
					"name" : "HELPSTRING",
					"value" : "Man documentation (DATAROOTDIR/man)"
				}
			],
			"type" : "PATH",
			"value" : ""
		},
		{
			"name" : "CMAKE_INSTALL_OLDINCLUDEDIR",
			"properties" : 
			[
				{
					"name" : "ADVANCED",
					"value" : "1"
				},
				{
					"name" : "HELPSTRING",
					"value" : "C header files for non-gcc (/usr/include)"
				}
			],
			"type" : "PATH",
			"value" : "/usr/include"
		},
		{
			"name" : "CMAKE_INSTALL_PREFIX",
			"properties" : 
			[
				{
					"name" : "HELPSTRING",
					"value" : "Install path prefix, prepended onto install directories."
				}
			],
			"type" : "PATH",
			"value" : "/usr/local"
		},
		{
			"name" : "CMAKE_INSTALL_RUNSTATEDIR",
			"properties" : 
			[
				{
					"name" : "ADVANCED",
					"value" : "1"
				},
				{
					"name" : "HELPSTRING",
					"value" : "Run-time variable data (LOCALSTATEDIR/run)"
				}
			],
			"type" : "PATH",
			"value" : ""
		},
		{
			"name" : "CMAKE_INSTALL_SBINDIR",
			"properties" : 
			[
				{
					"name" : "ADVANCED",
					"value" : "1"
				},
				{
					"name" : "HELPSTRING",
					"value" : "System admin executables (sbin)"
				}
			],
			"type" : "PATH",
			"value" : "sbin"
		},
		{
			"name" : "CMAKE_INSTALL_SHAREDSTATEDIR",
			"properties" : 
			[
				{
					"name" : "ADVANCED",
					"value" : "1"
				},
				{
					"name" : "HELPSTRING",
					"value" : "Modifiable architecture-independent data (com)"
				}
			],
			"type" : "PATH",
			"value" : "com"
		},
		{
			"name" : "CMAKE_INSTALL_SO_NO_EXE",
			"properties" : 
			[
				{
					"name" : "HELPSTRING",
					"value" : "Install .so files without execute permission."
				}
			],
			"type" : "INTERNAL",
			"value" : "1"
		},
		{
			"name" : "CMAKE_INSTALL_SYSCONFDIR",
			"properties" : 
			[
				{
					"name" : "ADVANCED",
					"value" : "1"
				},
				{
					"name" : "HELPSTRING",
					"value" : "Read-only single-machine data (etc)"
				}
			],
			"type" : "PATH",
			"value" : "etc"
		},
		{
			"name" : "CMAKE_LINKER",
			"properties" : 
			[
				{
					"name" : "ADVANCED",
					"value" : "1"
				},
				{
					"name" : "HELPSTRING",
					"value" : "Path to a program."
				}
			],
			"type" : "FILEPATH",
			"value" : "/usr/bin/ld"
		},
		{
			"name" : "CMAKE_MAKE_PROGRAM",
			"properties" : 
			[
				{
					"name" : "ADVANCED",
					"value" : "1"
				},
				{
					"name" : "HELPSTRING",
					"value" : "Path to a program."
				}
			],
			"type" : "FILEPATH",
			"value" : "/usr/bin/gmake"
		},
		{
			"name" : "CMAKE_MODULE_LINKER_FLAGS",
			"properties" : 
			[
				{
					"name" : "ADVANCED",
					"value" : "1"
				},
				{
					"name" : "HELPSTRING",
					"value" : "Flags used by the linker during the creation of modules during all build types."
				}
			],
			"type" : "STRING",
			"value" : ""
		},
		{
			"name" : "CMAKE_MODULE_LINKER_FLAGS_DEBUG",
			"properties" : 
			[
				{
					"name" : "ADVANCED",
					"value" : "1"
				},
				{
					"name" : "HELPSTRING",
					"value" : "Flags used by the linker during the creation of modules during DEBUG builds."
				}
			],
			"type" : "STRING",
			"value" : ""
		},
		{
			"name" : "CMAKE_MODULE_LINKER_FLAGS_MINSIZEREL",
			"properties" : 
			[
				{
					"name" : "ADVANCED",
					"value" : "1"
				},
				{
					"name" : "HELPSTRING",
					"value" : "Flags used by the linker during the creation of modules during MINSIZEREL builds."
				}
			],
			"type" : "STRING",
			"value" : ""
		},
		{
			"name" : "CMAKE_MODULE_LINKER_FLAGS_RELEASE",
			"properties" : 
			[
				{
					"name" : "ADVANCED",
					"value" : "1"
				},
				{
					"name" : "HELPSTRING",
					"value" : "Flags used by the linker during the creation of modules during RELEASE builds."
				}
			],
			"type" : "STRING",
			"value" : ""
		},
		{
			"name" : "CMAKE_MODULE_LINKER_FLAGS_RELWITHDEBINFO",
			"properties" : 
			[
				{
					"name" : "ADVANCED",
					"value" : "1"
				},
				{
					"name" : "HELPSTRING",
					"value" : "Flags used by the linker during the creation of modules during RELWITHDEBINFO builds."
				}
			],
			"type" : "STRING",
			"value" : ""
		},
		{
			"name" : "CMAKE_NM",
			"properties" : 
			[
				{
					"name" : "ADVANCED",
					"value" : "1"
				},
				{
					"name" : "HELPSTRING",
					"value" : "Path to a program."
				}
			],
			"type" : "FILEPATH",
			"value" : "/usr/bin/nm"
		},
		{
			"name" : "CMAKE_NUMBER_OF_MAKEFILES",
			"properties" : 
			[
				{
					"name" : "HELPSTRING",
					"value" : "number of local generators"
				}
			],
			"type" : "INTERNAL",
			"value" : "27"
		},
		{
			"name" : "CMAKE_OBJCOPY",
			"properties" : 
			[
				{
					"name" : "ADVANCED",
					"value" : "1"
				},
				{
					"name" : "HELPSTRING",
					"value" : "Path to a program."
				}
			],
			"type" : "FILEPATH",
			"value" : "/usr/bin/objcopy"
		},
		{
			"name" : "CMAKE_OBJDUMP",
			"properties" : 
			[
				{
					"name" : "ADVANCED",
					"value" : "1"
				},
				{
					"name" : "HELPSTRING",
					"value" : "Path to a program."
				}
			],
			"type" : "FILEPATH",
			"value" : "/usr/bin/objdump"
		},
		{
			"name" : "CMAKE_PLATFORM_INFO_INITIALIZED",
			"properties" : 
			[
				{
					"name" : "HELPSTRING",
					"value" : "Platform information initialized"
				}
			],
			"type" : "INTERNAL",
			"value" : "1"
		},
		{
			"name" : "CMAKE_PROJECT_DESCRIPTION",
			"properties" : 
			[
				{
					"name" : "HELPSTRING",
					"value" : "Value Computed by CMake"
				}
			],
			"type" : "STATIC",
			"value" : ""
		},
		{
			"name" : "CMAKE_PROJECT_HOMEPAGE_URL",
			"properties" : 
			[
				{
					"name" : "HELPSTRING",
					"value" : "Value Computed by CMake"
				}
			],
			"type" : "STATIC",
			"value" : ""
		},
		{
			"name" : "CMAKE_PROJECT_NAME",
			"properties" : 
			[
				{
					"name" : "HELPSTRING",
					"value" : "Value Computed by CMake"
				}
			],
			"type" : "STATIC",
			"value" : "millemiglia"
		},
		{
			"name" : "CMAKE_PROJECT_VERSION",
			"properties" : 
			[
				{
					"name" : "HELPSTRING",
					"value" : "Value Computed by CMake"
				}
			],
			"type" : "STATIC",
			"value" : "0.0.1"
		},
		{
			"name" : "CMAKE_PROJECT_VERSION_MAJOR",
			"properties" : 
			[
				{
					"name" : "HELPSTRING",
					"value" : "Value Computed by CMake"
				}
			],
			"type" : "STATIC",
			"value" : "0"
		},
		{
			"name" : "CMAKE_PROJECT_VERSION_MINOR",
			"properties" : 
			[
				{
					"name" : "HELPSTRING",
					"value" : "Value Computed by CMake"
				}
			],
			"type" : "STATIC",
			"value" : "0"
		},
		{
			"name" : "CMAKE_PROJECT_VERSION_PATCH",
			"properties" : 
			[
				{
					"name" : "HELPSTRING",
					"value" : "Value Computed by CMake"
				}
			],
			"type" : "STATIC",
			"value" : "1"
		},
		{
			"name" : "CMAKE_PROJECT_VERSION_TWEAK",
			"properties" : 
			[
				{
					"name" : "HELPSTRING",
					"value" : "Value Computed by CMake"
				}
			],
			"type" : "STATIC",
			"value" : ""
		},
		{
			"name" : "CMAKE_RANLIB",
			"properties" : 
			[
				{
					"name" : "ADVANCED",
					"value" : "1"
				},
				{
					"name" : "HELPSTRING",
					"value" : "Path to a program."
				}
			],
			"type" : "FILEPATH",
			"value" : "/usr/bin/ranlib"
		},
		{
			"name" : "CMAKE_READELF",
			"properties" : 
			[
				{
					"name" : "ADVANCED",
					"value" : "1"
				},
				{
					"name" : "HELPSTRING",
					"value" : "Path to a program."
				}
			],
			"type" : "FILEPATH",
			"value" : "/usr/bin/readelf"
		},
		{
			"name" : "CMAKE_ROOT",
			"properties" : 
			[
				{
					"name" : "HELPSTRING",
					"value" : "Path to CMake installation."
				}
			],
			"type" : "INTERNAL",
			"value" : "/usr/share/cmake-3.27"
		},
		{
			"name" : "CMAKE_SHARED_LINKER_FLAGS",
			"properties" : 
			[
				{
					"name" : "ADVANCED",
					"value" : "1"
				},
				{
					"name" : "HELPSTRING",
					"value" : "Flags used by the linker during the creation of shared libraries during all build types."
				}
			],
			"type" : "STRING",
			"value" : ""
		},
		{
			"name" : "CMAKE_SHARED_LINKER_FLAGS_DEBUG",
			"properties" : 
			[
				{
					"name" : "ADVANCED",
					"value" : "1"
				},
				{
					"name" : "HELPSTRING",
					"value" : "Flags used by the linker during the creation of shared libraries during DEBUG builds."
				}
			],
			"type" : "STRING",
			"value" : ""
		},
		{
			"name" : "CMAKE_SHARED_LINKER_FLAGS_MINSIZEREL",
			"properties" : 
			[
				{
					"name" : "ADVANCED",
					"value" : "1"
				},
				{
					"name" : "HELPSTRING",
					"value" : "Flags used by the linker during the creation of shared libraries during MINSIZEREL builds."
				}
			],
			"type" : "STRING",
			"value" : ""
		},
		{
			"name" : "CMAKE_SHARED_LINKER_FLAGS_RELEASE",
			"properties" : 
			[
				{
					"name" : "ADVANCED",
					"value" : "1"
				},
				{
					"name" : "HELPSTRING",
					"value" : "Flags used by the linker during the creation of shared libraries during RELEASE builds."
				}
			],
			"type" : "STRING",
			"value" : ""
		},
		{
			"name" : "CMAKE_SHARED_LINKER_FLAGS_RELWITHDEBINFO",
			"properties" : 
			[
				{
					"name" : "ADVANCED",
					"value" : "1"
				},
				{
					"name" : "HELPSTRING",
					"value" : "Flags used by the linker during the creation of shared libraries during RELWITHDEBINFO builds."
				}
			],
			"type" : "STRING",
			"value" : ""
		},
		{
			"name" : "CMAKE_SKIP_INSTALL_RPATH",
			"properties" : 
			[
				{
					"name" : "ADVANCED",
					"value" : "1"
				},
				{
					"name" : "HELPSTRING",
					"value" : "If set, runtime paths are not added when installing shared libraries, but are added when building."
				}
			],
			"type" : "BOOL",
			"value" : "NO"
		},
		{
			"name" : "CMAKE_SKIP_RPATH",
			"properties" : 
			[
				{
					"name" : "ADVANCED",
					"value" : "1"
				},
				{
					"name" : "HELPSTRING",
					"value" : "If set, runtime paths are not added when using shared libraries."
				}
			],
			"type" : "BOOL",
			"value" : "NO"
		},
		{
			"name" : "CMAKE_STATIC_LINKER_FLAGS",
			"properties" : 
			[
				{
					"name" : "ADVANCED",
					"value" : "1"
				},
				{
					"name" : "HELPSTRING",
					"value" : "Flags used by the linker during the creation of static libraries during all build types."
				}
			],
			"type" : "STRING",
			"value" : ""
		},
		{
			"name" : "CMAKE_STATIC_LINKER_FLAGS_DEBUG",
			"properties" : 
			[
				{
					"name" : "ADVANCED",
					"value" : "1"
				},
				{
					"name" : "HELPSTRING",
					"value" : "Flags used by the linker during the creation of static libraries during DEBUG builds."
				}
			],
			"type" : "STRING",
			"value" : ""
		},
		{
			"name" : "CMAKE_STATIC_LINKER_FLAGS_MINSIZEREL",
			"properties" : 
			[
				{
					"name" : "ADVANCED",
					"value" : "1"
				},
				{
					"name" : "HELPSTRING",
					"value" : "Flags used by the linker during the creation of static libraries during MINSIZEREL builds."
				}
			],
			"type" : "STRING",
			"value" : ""
		},
		{
			"name" : "CMAKE_STATIC_LINKER_FLAGS_RELEASE",
			"properties" : 
			[
				{
					"name" : "ADVANCED",
					"value" : "1"
				},
				{
					"name" : "HELPSTRING",
					"value" : "Flags used by the linker during the creation of static libraries during RELEASE builds."
				}
			],
			"type" : "STRING",
			"value" : ""
		},
		{
			"name" : "CMAKE_STATIC_LINKER_FLAGS_RELWITHDEBINFO",
			"properties" : 
			[
				{
					"name" : "ADVANCED",
					"value" : "1"
				},
				{
					"name" : "HELPSTRING",
					"value" : "Flags used by the linker during the creation of static libraries during RELWITHDEBINFO builds."
				}
			],
			"type" : "STRING",
			"value" : ""
		},
		{
			"name" : "CMAKE_STRIP",
			"properties" : 
			[
				{
					"name" : "ADVANCED",
					"value" : "1"
				},
				{
					"name" : "HELPSTRING",
					"value" : "Path to a program."
				}
			],
			"type" : "FILEPATH",
			"value" : "/usr/bin/strip"
		},
		{
			"name" : "CMAKE_TAPI",
			"properties" : 
			[
				{
					"name" : "ADVANCED",
					"value" : "1"
				},
				{
					"name" : "HELPSTRING",
					"value" : "Path to a program."
				}
			],
			"type" : "FILEPATH",
			"value" : "CMAKE_TAPI-NOTFOUND"
		},
		{
			"name" : "CMAKE_UNAME",
			"properties" : 
			[
				{
					"name" : "HELPSTRING",
					"value" : "uname command"
				}
			],
			"type" : "INTERNAL",
			"value" : "/usr/bin/uname"
		},
		{
			"name" : "CMAKE_VERBOSE_MAKEFILE",
			"properties" : 
			[
				{
					"name" : "ADVANCED",
					"value" : "1"
				},
				{
					"name" : "HELPSTRING",
					"value" : "If this value is on, makefiles will be generated without the .SILENT directive, and all commands will be echoed to the console during the make.  This is useful for debugging only. With Visual Studio IDE projects all commands are done without /nologo."
				}
			],
			"type" : "BOOL",
			"value" : "FALSE"
		},
		{
			"name" : "COVERAGE_COMMAND",
			"properties" : 
			[
				{
					"name" : "ADVANCED",
					"value" : "1"
				},
				{
					"name" : "HELPSTRING",
					"value" : "Path to the coverage program that CTest uses for performing coverage inspection"
				}
			],
			"type" : "FILEPATH",
			"value" : "/usr/bin/gcov"
		},
		{
			"name" : "COVERAGE_EXTRA_FLAGS",
			"properties" : 
			[
				{
					"name" : "ADVANCED",
					"value" : "1"
				},
				{
					"name" : "HELPSTRING",
					"value" : "Extra command line flags to pass to the coverage tool"
				}
			],
			"type" : "STRING",
			"value" : "-l"
		},
		{
			"name" : "CTEST_SUBMIT_RETRY_COUNT",
			"properties" : 
			[
				{
					"name" : "ADVANCED",
					"value" : "1"
				},
				{
					"name" : "HELPSTRING",
					"value" : "How many times to retry timed-out CTest submissions."
				}
			],
			"type" : "STRING",
			"value" : "3"
		},
		{
			"name" : "CTEST_SUBMIT_RETRY_DELAY",
			"properties" : 
			[
				{
					"name" : "ADVANCED",
					"value" : "1"
				},
				{
					"name" : "HELPSTRING",
					"value" : "How long to wait between timed-out CTest submissions."
				}
			],
			"type" : "STRING",
			"value" : "5"
		},
		{
			"name" : "CVSCOMMAND",
			"properties" : 
			[
				{
					"name" : "ADVANCED",
					"value" : "1"
				},
				{
					"name" : "HELPSTRING",
					"value" : ""
				}
			],
			"type" : "UNINITIALIZED",
			"value" : ""
		},
		{
			"name" : "CVS_UPDATE_OPTIONS",
			"properties" : 
			[
				{
					"name" : "ADVANCED",
					"value" : "1"
				},
				{
					"name" : "HELPSTRING",
					"value" : ""
				}
			],
			"type" : "UNINITIALIZED",
			"value" : ""
		},
		{
			"name" : "DART_TESTING_TIMEOUT",
			"properties" : 
			[
				{
					"name" : "ADVANCED",
					"value" : "1"
				},
				{
					"name" : "HELPSTRING",
					"value" : "Maximum time allowed before CTest will kill the test."
				}
			],
			"type" : "STRING",
			"value" : "1500"
		},
		{
			"name" : "EXECINFO_LIBRARY",
			"properties" : 
			[
				{
					"name" : "HELPSTRING",
					"value" : "Path to a library."
				}
			],
			"type" : "FILEPATH",
			"value" : "EXECINFO_LIBRARY-NOTFOUND"
		},
		{
			"name" : "FETCHCONTENT_BASE_DIR",
			"properties" : 
			[
				{
					"name" : "HELPSTRING",
					"value" : "Directory under which to collect all populated content"
				}
			],
			"type" : "PATH",
			"value" : "/home/aymanelotfi/Documents/millemiglia/build/_deps"
		},
		{
			"name" : "FETCHCONTENT_FULLY_DISCONNECTED",
			"properties" : 
			[
				{
					"name" : "HELPSTRING",
					"value" : "Disables all attempts to download or update content and assumes source dirs already exist"
				}
			],
			"type" : "BOOL",
			"value" : "OFF"
		},
		{
			"name" : "FETCHCONTENT_QUIET",
			"properties" : 
			[
				{
					"name" : "HELPSTRING",
					"value" : "Enables QUIET option for all content population"
				}
			],
			"type" : "BOOL",
			"value" : "ON"
		},
		{
			"name" : "FETCHCONTENT_SOURCE_DIR_ABSEIL-CPP",
			"properties" : 
			[
				{
					"name" : "HELPSTRING",
					"value" : "When not empty, overrides where to find pre-populated content for abseil-cpp"
				}
			],
			"type" : "PATH",
			"value" : ""
		},
		{
			"name" : "FETCHCONTENT_SOURCE_DIR_PROTOBUF",
			"properties" : 
			[
				{
					"name" : "HELPSTRING",
					"value" : "When not empty, overrides where to find pre-populated content for Protobuf"
				}
			],
			"type" : "PATH",
			"value" : ""
		},
		{
			"name" : "FETCHCONTENT_UPDATES_DISCONNECTED",
			"properties" : 
			[
				{
					"name" : "HELPSTRING",
					"value" : "Enables UPDATE_DISCONNECTED behavior for all content population"
				}
			],
			"type" : "BOOL",
			"value" : "OFF"
		},
		{
			"name" : "FETCHCONTENT_UPDATES_DISCONNECTED_ABSEIL-CPP",
			"properties" : 
			[
				{
					"name" : "HELPSTRING",
					"value" : "Enables UPDATE_DISCONNECTED behavior just for population of abseil-cpp"
				}
			],
			"type" : "BOOL",
			"value" : "OFF"
		},
		{
			"name" : "FETCHCONTENT_UPDATES_DISCONNECTED_PROTOBUF",
			"properties" : 
			[
				{
					"name" : "HELPSTRING",
					"value" : "Enables UPDATE_DISCONNECTED behavior just for population of Protobuf"
				}
			],
			"type" : "BOOL",
			"value" : "OFF"
		},
		{
			"name" : "FIND_PACKAGE_MESSAGE_DETAILS_Threads",
			"properties" : 
			[
				{
					"name" : "HELPSTRING",
					"value" : "Details about finding Threads"
				}
			],
			"type" : "INTERNAL",
			"value" : "[TRUE][v()]"
		},
		{
			"name" : "FIND_PACKAGE_MESSAGE_DETAILS_ZLIB",
			"properties" : 
			[
				{
					"name" : "HELPSTRING",
					"value" : "Details about finding ZLIB"
				}
			],
			"type" : "INTERNAL",
			"value" : "[/usr/lib/x86_64-linux-gnu/libz.so][/usr/include][c ][v1.3()]"
		},
		{
			"name" : "GITCOMMAND",
			"properties" : 
			[
				{
					"name" : "ADVANCED",
					"value" : "1"
				},
				{
					"name" : "HELPSTRING",
					"value" : "Path to a program."
				}
			],
			"type" : "FILEPATH",
			"value" : "/usr/bin/git"
		},
		{
			"name" : "GIT_EXECUTABLE",
			"properties" : 
			[
				{
					"name" : "ADVANCED",
					"value" : "1"
				},
				{
					"name" : "HELPSTRING",
					"value" : "Git command line client"
				}
			],
			"type" : "FILEPATH",
			"value" : "/usr/bin/git"
		},
		{
			"name" : "HGCOMMAND",
			"properties" : 
			[
				{
					"name" : "ADVANCED",
					"value" : "1"
				},
				{
					"name" : "HELPSTRING",
					"value" : ""
				}
			],
			"type" : "UNINITIALIZED",
			"value" : ""
		},
		{
			"name" : "LIBRT",
			"properties" : 
			[
				{
					"name" : "HELPSTRING",
					"value" : "Path to a library."
				}
			],
			"type" : "FILEPATH",
			"value" : "/usr/lib/x86_64-linux-gnu/librt.a"
		},
		{
			"name" : "MAKECOMMAND",
			"properties" : 
			[
				{
					"name" : "ADVANCED",
					"value" : "1"
				},
				{
					"name" : "HELPSTRING",
					"value" : "Command to build the project"
				}
			],
			"type" : "STRING",
			"value" : "/usr/bin/cmake --build . --config \"${CTEST_CONFIGURATION_TYPE}\""
		},
		{
			"name" : "MEMORYCHECK_COMMAND",
			"properties" : 
			[
				{
					"name" : "ADVANCED",
					"value" : "1"
				},
				{
					"name" : "HELPSTRING",
					"value" : "Path to the memory checking command, used for memory error detection."
				}
			],
			"type" : "FILEPATH",
			"value" : "MEMORYCHECK_COMMAND-NOTFOUND"
		},
		{
			"name" : "MEMORYCHECK_SUPPRESSIONS_FILE",
			"properties" : 
			[
				{
					"name" : "ADVANCED",
					"value" : "1"
				},
				{
					"name" : "HELPSTRING",
					"value" : "File that contains suppressions for the memory checker"
				}
			],
			"type" : "FILEPATH",
			"value" : ""
		},
		{
			"name" : "P4COMMAND",
			"properties" : 
			[
				{
					"name" : "ADVANCED",
					"value" : "1"
				},
				{
					"name" : "HELPSTRING",
					"value" : ""
				}
			],
			"type" : "UNINITIALIZED",
			"value" : ""
		},
		{
			"name" : "Protobuf_DIR",
			"properties" : 
			[
				{
					"name" : "HELPSTRING",
					"value" : "Redirected by FetchContent"
				}
			],
			"type" : "INTERNAL",
			"value" : "/home/aymanelotfi/Documents/millemiglia/build/CMakeFiles/pkgRedirects"
		},
		{
			"name" : "SITE",
			"properties" : 
			[
				{
					"name" : "ADVANCED",
					"value" : "1"
				},
				{
					"name" : "HELPSTRING",
					"value" : "Name of the computer/site where compile is being run"
				}
			],
			"type" : "STRING",
			"value" : "aymanelotfi"
		},
		{
			"name" : "SVNCOMMAND",
			"properties" : 
			[
				{
					"name" : "ADVANCED",
					"value" : "1"
				},
				{
					"name" : "HELPSTRING",
					"value" : ""
				}
			],
			"type" : "UNINITIALIZED",
			"value" : ""
		},
		{
			"name" : "ZLIB_INCLUDE_DIR",
			"properties" : 
			[
				{
					"name" : "ADVANCED",
					"value" : "1"
				},
				{
					"name" : "HELPSTRING",
					"value" : "Path to a file."
				}
			],
			"type" : "PATH",
			"value" : "/usr/include"
		},
		{
			"name" : "ZLIB_LIBRARY_DEBUG",
			"properties" : 
			[
				{
					"name" : "ADVANCED",
					"value" : "1"
				},
				{
					"name" : "HELPSTRING",
					"value" : "Path to a library."
				}
			],
			"type" : "FILEPATH",
			"value" : "ZLIB_LIBRARY_DEBUG-NOTFOUND"
		},
		{
			"name" : "ZLIB_LIBRARY_RELEASE",
			"properties" : 
			[
				{
					"name" : "ADVANCED",
					"value" : "1"
				},
				{
					"name" : "HELPSTRING",
					"value" : "Path to a library."
				}
			],
			"type" : "FILEPATH",
			"value" : "/usr/lib/x86_64-linux-gnu/libz.so"
		},
		{
			"name" : "_CMAKE_LINKER_PUSHPOP_STATE_SUPPORTED",
			"properties" : 
			[
				{
					"name" : "HELPSTRING",
					"value" : "linker supports push/pop state"
				}
			],
			"type" : "INTERNAL",
			"value" : "TRUE"
		},
		{
			"name" : "_GNUInstallDirs_LAST_CMAKE_INSTALL_PREFIX",
			"properties" : 
			[
				{
					"name" : "HELPSTRING",
					"value" : "CMAKE_INSTALL_PREFIX during last run"
				}
			],
			"type" : "INTERNAL",
			"value" : "/usr/local"
		},
		{
			"name" : "absl_BINARY_DIR",
			"properties" : 
			[
				{
					"name" : "HELPSTRING",
					"value" : "Value Computed by CMake"
				}
			],
			"type" : "STATIC",
			"value" : "/home/aymanelotfi/Documents/millemiglia/build/_deps/abseil-cpp-build"
		},
		{
			"name" : "absl_IS_TOP_LEVEL",
			"properties" : 
			[
				{
					"name" : "HELPSTRING",
					"value" : "Value Computed by CMake"
				}
			],
			"type" : "STATIC",
			"value" : "OFF"
		},
		{
			"name" : "absl_SOURCE_DIR",
			"properties" : 
			[
				{
					"name" : "HELPSTRING",
					"value" : "Value Computed by CMake"
				}
			],
			"type" : "STATIC",
			"value" : "/home/aymanelotfi/Documents/millemiglia/build/_deps/abseil-cpp-src"
		},
		{
			"name" : "bad_any_cast_impl_LIB_DEPENDS",
			"properties" : 
			[
				{
					"name" : "HELPSTRING",
					"value" : "Dependencies for the target"
				}
			],
			"type" : "STATIC",
			"value" : "general;absl::raw_logging_internal;"
		},
		{
			"name" : "bad_optional_access_LIB_DEPENDS",
			"properties" : 
			[
				{
					"name" : "HELPSTRING",
					"value" : "Dependencies for the target"
				}
			],
			"type" : "STATIC",
			"value" : "general;absl::raw_logging_internal;"
		},
		{
			"name" : "bad_variant_access_LIB_DEPENDS",
			"properties" : 
			[
				{
					"name" : "HELPSTRING",
					"value" : "Dependencies for the target"
				}
			],
			"type" : "STATIC",
			"value" : "general;absl::raw_logging_internal;"
		},
		{
			"name" : "base_LIB_DEPENDS",
			"properties" : 
			[
				{
					"name" : "HELPSTRING",
					"value" : "Dependencies for the target"
				}
			],
			"type" : "STATIC",
			"value" : "general;absl::log_severity;general;absl::raw_logging_internal;general;absl::spinlock_wait;general;absl::type_traits;"
		},
		{
			"name" : "cord_LIB_DEPENDS",
			"properties" : 
			[
				{
					"name" : "HELPSTRING",
					"value" : "Dependencies for the target"
				}
			],
			"type" : "STATIC",
			"value" : "general;absl::base;general;absl::cord_internal;general;absl::cordz_functions;general;absl::cordz_info;general;absl::crc32c;general;absl::crc_cord_state;general;absl::optional;general;absl::raw_logging_internal;general;absl::span;general;absl::strings;"
		},
		{
			"name" : "cord_internal_LIB_DEPENDS",
			"properties" : 
			[
				{
					"name" : "HELPSTRING",
					"value" : "Dependencies for the target"
				}
			],
			"type" : "STATIC",
			"value" : "general;absl::crc_cord_state;general;absl::raw_logging_internal;general;absl::strings;general;absl::throw_delegate;"
		},
		{
			"name" : "cordz_functions_LIB_DEPENDS",
			"properties" : 
			[
				{
					"name" : "HELPSTRING",
					"value" : "Dependencies for the target"
				}
			],
			"type" : "STATIC",
			"value" : "general;absl::exponential_biased;general;absl::raw_logging_internal;"
		},
		{
			"name" : "cordz_handle_LIB_DEPENDS",
			"properties" : 
			[
				{
					"name" : "HELPSTRING",
					"value" : "Dependencies for the target"
				}
			],
			"type" : "STATIC",
			"value" : "general;absl::base;general;absl::raw_logging_internal;general;absl::synchronization;"
		},
		{
			"name" : "cordz_info_LIB_DEPENDS",
			"properties" : 
			[
				{
					"name" : "HELPSTRING",
					"value" : "Dependencies for the target"
				}
			],
			"type" : "STATIC",
			"value" : "general;absl::base;general;absl::cord_internal;general;absl::cordz_functions;general;absl::cordz_handle;general;absl::span;general;absl::raw_logging_internal;general;absl::stacktrace;general;absl::synchronization;general;absl::time;"
		},
		{
			"name" : "cordz_sample_token_LIB_DEPENDS",
			"properties" : 
			[
				{
					"name" : "HELPSTRING",
					"value" : "Dependencies for the target"
				}
			],
			"type" : "STATIC",
			"value" : "general;absl::cordz_handle;general;absl::cordz_info;"
		},
		{
			"name" : "crc32c_LIB_DEPENDS",
			"properties" : 
			[
				{
					"name" : "HELPSTRING",
					"value" : "Dependencies for the target"
				}
			],
			"type" : "STATIC",
			"value" : "general;absl::crc_cpu_detect;general;absl::crc_internal;general;absl::non_temporal_memcpy;general;absl::str_format;general;absl::strings;"
		},
		{
			"name" : "crc_cord_state_LIB_DEPENDS",
			"properties" : 
			[
				{
					"name" : "HELPSTRING",
					"value" : "Dependencies for the target"
				}
			],
			"type" : "STATIC",
			"value" : "general;absl::crc32c;general;absl::strings;"
		},
		{
			"name" : "crc_cpu_detect_LIB_DEPENDS",
			"properties" : 
			[
				{
					"name" : "HELPSTRING",
					"value" : "Dependencies for the target"
				}
			],
			"type" : "STATIC",
			"value" : "general;absl::base;"
		},
		{
			"name" : "crc_internal_LIB_DEPENDS",
			"properties" : 
			[
				{
					"name" : "HELPSTRING",
					"value" : "Dependencies for the target"
				}
			],
			"type" : "STATIC",
			"value" : "general;absl::crc_cpu_detect;general;absl::raw_logging_internal;general;absl::memory;general;absl::bits;"
		},
		{
			"name" : "debugging_internal_LIB_DEPENDS",
			"properties" : 
			[
				{
					"name" : "HELPSTRING",
					"value" : "Dependencies for the target"
				}
			],
			"type" : "STATIC",
			"value" : "general;absl::raw_logging_internal;"
		},
		{
			"name" : "demangle_internal_LIB_DEPENDS",
			"properties" : 
			[
				{
					"name" : "HELPSTRING",
					"value" : "Dependencies for the target"
				}
			],
			"type" : "STATIC",
			"value" : "general;absl::base;"
		},
		{
			"name" : "die_if_null_LIB_DEPENDS",
			"properties" : 
			[
				{
					"name" : "HELPSTRING",
					"value" : "Dependencies for the target"
				}
			],
			"type" : "STATIC",
			"value" : "general;absl::log;general;absl::strings;"
		},
		{
			"name" : "examine_stack_LIB_DEPENDS",
			"properties" : 
			[
				{
					"name" : "HELPSTRING",
					"value" : "Dependencies for the target"
				}
			],
			"type" : "STATIC",
			"value" : "general;absl::stacktrace;general;absl::symbolize;general;absl::raw_logging_internal;"
		},
		{
			"name" : "failure_signal_handler_LIB_DEPENDS",
			"properties" : 
			[
				{
					"name" : "HELPSTRING",
					"value" : "Dependencies for the target"
				}
			],
			"type" : "STATIC",
			"value" : "general;absl::examine_stack;general;absl::stacktrace;general;absl::base;general;absl::raw_logging_internal;"
		},
		{
			"name" : "flags_commandlineflag_LIB_DEPENDS",
			"properties" : 
			[
				{
					"name" : "HELPSTRING",
					"value" : "Dependencies for the target"
				}
			],
			"type" : "STATIC",
			"value" : "general;absl::flags_commandlineflag_internal;general;absl::optional;general;absl::strings;"
		},
		{
			"name" : "flags_config_LIB_DEPENDS",
			"properties" : 
			[
				{
					"name" : "HELPSTRING",
					"value" : "Dependencies for the target"
				}
			],
			"type" : "STATIC",
			"value" : "general;absl::flags_program_name;general;absl::strings;general;absl::synchronization;"
		},
		{
			"name" : "flags_internal_LIB_DEPENDS",
			"properties" : 
			[
				{
					"name" : "HELPSTRING",
					"value" : "Dependencies for the target"
				}
			],
			"type" : "STATIC",
			"value" : "general;absl::base;general;absl::flags_commandlineflag;general;absl::flags_commandlineflag_internal;general;absl::flags_config;general;absl::flags_marshalling;general;absl::synchronization;general;absl::meta;general;absl::utility;"
		},
		{
			"name" : "flags_marshalling_LIB_DEPENDS",
			"properties" : 
			[
				{
					"name" : "HELPSTRING",
					"value" : "Dependencies for the target"
				}
			],
			"type" : "STATIC",
			"value" : "general;absl::log_severity;general;absl::int128;general;absl::optional;general;absl::strings;general;absl::str_format;"
		},
		{
			"name" : "flags_parse_LIB_DEPENDS",
			"properties" : 
			[
				{
					"name" : "HELPSTRING",
					"value" : "Dependencies for the target"
				}
			],
			"type" : "STATIC",
			"value" : "general;absl::flags_config;general;absl::flags_commandlineflag;general;absl::flags_commandlineflag_internal;general;absl::flags_internal;general;absl::flags_private_handle_accessor;general;absl::flags_program_name;general;absl::flags_reflection;general;absl::flags_usage;general;absl::strings;general;absl::synchronization;"
		},
		{
			"name" : "flags_private_handle_accessor_LIB_DEPENDS",
			"properties" : 
			[
				{
					"name" : "HELPSTRING",
					"value" : "Dependencies for the target"
				}
			],
			"type" : "STATIC",
			"value" : "general;absl::flags_commandlineflag;general;absl::flags_commandlineflag_internal;general;absl::strings;"
		},
		{
			"name" : "flags_program_name_LIB_DEPENDS",
			"properties" : 
			[
				{
					"name" : "HELPSTRING",
					"value" : "Dependencies for the target"
				}
			],
			"type" : "STATIC",
			"value" : "general;absl::strings;general;absl::synchronization;"
		},
		{
			"name" : "flags_reflection_LIB_DEPENDS",
			"properties" : 
			[
				{
					"name" : "HELPSTRING",
					"value" : "Dependencies for the target"
				}
			],
			"type" : "STATIC",
			"value" : "general;absl::flags_commandlineflag;general;absl::flags_private_handle_accessor;general;absl::flags_config;general;absl::strings;general;absl::synchronization;"
		},
		{
			"name" : "flags_usage_LIB_DEPENDS",
			"properties" : 
			[
				{
					"name" : "HELPSTRING",
					"value" : "Dependencies for the target"
				}
			],
			"type" : "STATIC",
			"value" : "general;absl::flags_usage_internal;general;absl::raw_logging_internal;general;absl::strings;general;absl::synchronization;"
		},
		{
			"name" : "flags_usage_internal_LIB_DEPENDS",
			"properties" : 
			[
				{
					"name" : "HELPSTRING",
					"value" : "Dependencies for the target"
				}
			],
			"type" : "STATIC",
			"value" : "general;absl::flags_config;general;absl::flags_commandlineflag;general;absl::flags_internal;general;absl::flags_private_handle_accessor;general;absl::flags_program_name;general;absl::flags_reflection;general;absl::strings;general;absl::synchronization;"
		},
		{
			"name" : "graphcycles_internal_LIB_DEPENDS",
			"properties" : 
			[
				{
					"name" : "HELPSTRING",
					"value" : "Dependencies for the target"
				}
			],
			"type" : "STATIC",
			"value" : "general;absl::base;general;absl::malloc_internal;general;absl::raw_logging_internal;"
		},
		{
			"name" : "hash_LIB_DEPENDS",
			"properties" : 
			[
				{
					"name" : "HELPSTRING",
					"value" : "Dependencies for the target"
				}
			],
			"type" : "STATIC",
			"value" : "general;absl::bits;general;absl::city;general;absl::meta;general;absl::int128;general;absl::strings;general;absl::optional;general;absl::variant;general;absl::utility;general;absl::low_level_hash;"
		},
		{
			"name" : "hashtablez_sampler_LIB_DEPENDS",
			"properties" : 
			[
				{
					"name" : "HELPSTRING",
					"value" : "Dependencies for the target"
				}
			],
			"type" : "STATIC",
			"value" : "general;absl::base;general;absl::exponential_biased;general;absl::raw_logging_internal;general;absl::sample_recorder;general;absl::synchronization;general;absl::time;"
		},
		{
			"name" : "kernel_timeout_internal_LIB_DEPENDS",
			"properties" : 
			[
				{
					"name" : "HELPSTRING",
					"value" : "Dependencies for the target"
				}
			],
			"type" : "STATIC",
			"value" : "general;absl::base;general;absl::raw_logging_internal;general;absl::time;"
		},
		{
			"name" : "log_entry_LIB_DEPENDS",
			"properties" : 
			[
				{
					"name" : "HELPSTRING",
					"value" : "Dependencies for the target"
				}
			],
			"type" : "STATIC",
			"value" : "general;absl::log_severity;general;absl::span;general;absl::strings;general;absl::time;"
		},
		{
			"name" : "log_flags_LIB_DEPENDS",
			"properties" : 
			[
				{
					"name" : "HELPSTRING",
					"value" : "Dependencies for the target"
				}
			],
			"type" : "STATIC",
			"value" : "general;absl::log_globals;general;absl::log_severity;general;absl::flags_marshalling;general;absl::strings;general;absl::vlog_config_internal;"
		},
		{
			"name" : "log_globals_LIB_DEPENDS",
			"properties" : 
			[
				{
					"name" : "HELPSTRING",
					"value" : "Dependencies for the target"
				}
			],
			"type" : "STATIC",
			"value" : "general;absl::hash;general;absl::log_severity;general;absl::raw_logging_internal;general;absl::strings;general;absl::vlog_config_internal;"
		},
		{
			"name" : "log_initialize_LIB_DEPENDS",
			"properties" : 
			[
				{
					"name" : "HELPSTRING",
					"value" : "Dependencies for the target"
				}
			],
			"type" : "STATIC",
			"value" : "general;absl::log_globals;general;absl::log_internal_globals;general;absl::time;"
		},
		{
			"name" : "log_internal_check_op_LIB_DEPENDS",
			"properties" : 
			[
				{
					"name" : "HELPSTRING",
					"value" : "Dependencies for the target"
				}
			],
			"type" : "STATIC",
			"value" : "general;absl::log_internal_nullguard;general;absl::log_internal_nullstream;general;absl::log_internal_strip;general;absl::strings;"
		},
		{
			"name" : "log_internal_conditions_LIB_DEPENDS",
			"properties" : 
			[
				{
					"name" : "HELPSTRING",
					"value" : "Dependencies for the target"
				}
			],
			"type" : "STATIC",
			"value" : "general;absl::base;general;absl::log_internal_voidify;"
		},
		{
			"name" : "log_internal_fnmatch_LIB_DEPENDS",
			"properties" : 
			[
				{
					"name" : "HELPSTRING",
					"value" : "Dependencies for the target"
				}
			],
			"type" : "STATIC",
			"value" : "general;absl::strings;"
		},
		{
			"name" : "log_internal_format_LIB_DEPENDS",
			"properties" : 
			[
				{
					"name" : "HELPSTRING",
					"value" : "Dependencies for the target"
				}
			],
			"type" : "STATIC",
			"value" : "general;absl::log_internal_append_truncated;general;absl::log_internal_globals;general;absl::log_severity;general;absl::strings;general;absl::str_format;general;absl::time;general;absl::span;"
		},
		{
			"name" : "log_internal_globals_LIB_DEPENDS",
			"properties" : 
			[
				{
					"name" : "HELPSTRING",
					"value" : "Dependencies for the target"
				}
			],
			"type" : "STATIC",
			"value" : "general;absl::log_severity;general;absl::raw_logging_internal;general;absl::strings;general;absl::time;"
		},
		{
			"name" : "log_internal_log_sink_set_LIB_DEPENDS",
			"properties" : 
			[
				{
					"name" : "HELPSTRING",
					"value" : "Dependencies for the target"
				}
			],
			"type" : "STATIC",
			"value" : "general;absl::base;general;absl::log_internal_globals;general;absl::log_globals;general;absl::log_entry;general;absl::log_severity;general;absl::log_sink;general;absl::raw_logging_internal;general;absl::synchronization;general;absl::span;general;absl::strings;"
		},
		{
			"name" : "log_internal_message_LIB_DEPENDS",
			"properties" : 
			[
				{
					"name" : "HELPSTRING",
					"value" : "Dependencies for the target"
				}
			],
			"type" : "STATIC",
			"value" : "general;absl::base;general;absl::examine_stack;general;absl::log_internal_append_truncated;general;absl::log_internal_format;general;absl::log_internal_globals;general;absl::log_internal_proto;general;absl::log_internal_log_sink_set;general;absl::log_internal_nullguard;general;absl::log_globals;general;absl::log_entry;general;absl::log_severity;general;absl::log_sink;general;absl::log_sink_registry;general;absl::memory;general;absl::raw_logging_internal;general;absl::strings;general;absl::strerror;general;absl::time;general;absl::span;"
		},
		{
			"name" : "log_internal_proto_LIB_DEPENDS",
			"properties" : 
			[
				{
					"name" : "HELPSTRING",
					"value" : "Dependencies for the target"
				}
			],
			"type" : "STATIC",
			"value" : "general;absl::base;general;absl::strings;general;absl::span;"
		},
		{
			"name" : "log_severity_LIB_DEPENDS",
			"properties" : 
			[
				{
					"name" : "HELPSTRING",
					"value" : "Dependencies for the target"
				}
			],
			"type" : "STATIC",
			"value" : "general;absl::config;general;absl::core_headers;"
		},
		{
			"name" : "log_sink_LIB_DEPENDS",
			"properties" : 
			[
				{
					"name" : "HELPSTRING",
					"value" : "Dependencies for the target"
				}
			],
			"type" : "STATIC",
			"value" : "general;absl::log_entry;"
		},
		{
			"name" : "low_level_hash_LIB_DEPENDS",
			"properties" : 
			[
				{
					"name" : "HELPSTRING",
					"value" : "Dependencies for the target"
				}
			],
			"type" : "STATIC",
			"value" : "general;absl::int128;"
		},
		{
			"name" : "malloc_internal_LIB_DEPENDS",
			"properties" : 
			[
				{
					"name" : "HELPSTRING",
					"value" : "Dependencies for the target"
				}
			],
			"type" : "STATIC",
			"value" : "general;absl::base;general;absl::base_internal;general;absl::raw_logging_internal;"
		},
		{
			"name" : "millemiglia_BINARY_DIR",
			"properties" : 
			[
				{
					"name" : "HELPSTRING",
					"value" : "Value Computed by CMake"
				}
			],
			"type" : "STATIC",
			"value" : "/home/aymanelotfi/Documents/millemiglia/build"
		},
		{
			"name" : "millemiglia_IS_TOP_LEVEL",
			"properties" : 
			[
				{
					"name" : "HELPSTRING",
					"value" : "Value Computed by CMake"
				}
			],
			"type" : "STATIC",
			"value" : "ON"
		},
		{
			"name" : "millemiglia_SOURCE_DIR",
			"properties" : 
			[
				{
					"name" : "HELPSTRING",
					"value" : "Value Computed by CMake"
				}
			],
			"type" : "STATIC",
			"value" : "/home/aymanelotfi/Documents/millemiglia"
		},
		{
			"name" : "periodic_sampler_LIB_DEPENDS",
			"properties" : 
			[
				{
					"name" : "HELPSTRING",
					"value" : "Dependencies for the target"
				}
			],
			"type" : "STATIC",
			"value" : "general;absl::exponential_biased;"
		},
		{
			"name" : "protobuf_ABSL_PROVIDER",
			"properties" : 
			[
				{
					"name" : "HELPSTRING",
					"value" : "Provider of absl library"
				},
				{
					"name" : "STRINGS",
					"value" : "module;package"
				}
			],
			"type" : "STRING",
			"value" : "module"
		},
		{
			"name" : "protobuf_ALLOW_CCACHE",
			"properties" : 
			[
				{
					"name" : "HELPSTRING",
					"value" : "Adjust build flags to allow for ccache support."
				}
			],
			"type" : "BOOL",
			"value" : "OFF"
		},
		{
			"name" : "protobuf_BINARY_DIR",
			"properties" : 
			[
				{
					"name" : "HELPSTRING",
					"value" : "Value Computed by CMake"
				}
			],
			"type" : "STATIC",
			"value" : "/home/aymanelotfi/Documents/millemiglia/build/_deps/protobuf-build"
		},
		{
			"name" : "protobuf_BUILD_CONFORMANCE",
			"properties" : 
			[
				{
					"name" : "HELPSTRING",
					"value" : "Build conformance tests"
				}
			],
			"type" : "BOOL",
			"value" : "OFF"
		},
		{
			"name" : "protobuf_BUILD_EXAMPLES",
			"properties" : 
			[
				{
					"name" : "HELPSTRING",
					"value" : "Build examples"
				}
			],
			"type" : "BOOL",
			"value" : "OFF"
		},
		{
			"name" : "protobuf_BUILD_LIBPROTOC",
			"properties" : 
			[
				{
					"name" : "HELPSTRING",
					"value" : "Build libprotoc"
				}
			],
			"type" : "BOOL",
			"value" : "OFF"
		},
		{
			"name" : "protobuf_BUILD_PROTOBUF_BINARIES",
			"properties" : 
			[
				{
					"name" : "HELPSTRING",
					"value" : "Build protobuf libraries and protoc compiler"
				}
			],
			"type" : "BOOL",
			"value" : "ON"
		},
		{
			"name" : "protobuf_BUILD_PROTOC_BINARIES",
			"properties" : 
			[
				{
					"name" : "HELPSTRING",
					"value" : "Build libprotoc and protoc compiler"
				}
			],
			"type" : "BOOL",
			"value" : "ON"
		},
		{
			"name" : "protobuf_BUILD_SHARED_LIBS",
			"properties" : 
			[
				{
					"name" : "HELPSTRING",
					"value" : "Build Shared Libraries"
				}
			],
			"type" : "BOOL",
			"value" : "OFF"
		},
		{
			"name" : "protobuf_CMAKE_SUBDIR",
			"properties" : 
			[
				{
					"name" : "ADVANCED",
					"value" : "1"
				},
				{
					"name" : "HELPSTRING",
					"value" : "Subdirectory in which to install cmake configuration files"
				}
			],
			"type" : "STRING",
			"value" : "cmake/protobuf"
		},
		{
			"name" : "protobuf_DEBUG_POSTFIX",
			"properties" : 
			[
				{
					"name" : "ADVANCED",
					"value" : "1"
				},
				{
					"name" : "HELPSTRING",
					"value" : "Default debug postfix"
				}
			],
			"type" : "STRING",
			"value" : "d"
		},
		{
			"name" : "protobuf_DISABLE_RTTI",
			"properties" : 
			[
				{
					"name" : "HELPSTRING",
					"value" : "Remove runtime type information in the binaries"
				}
			],
			"type" : "BOOL",
			"value" : "OFF"
		},
		{
			"name" : "protobuf_HAVE_BUILTIN_ATOMICS",
			"properties" : 
			[
				{
					"name" : "HELPSTRING",
					"value" : "Test protobuf_HAVE_BUILTIN_ATOMICS"
				}
			],
			"type" : "INTERNAL",
			"value" : "1"
		},
		{
			"name" : "protobuf_HAVE_LD_VERSION_SCRIPT",
			"properties" : 
			[
				{
					"name" : "HELPSTRING",
					"value" : "Test protobuf_HAVE_LD_VERSION_SCRIPT"
				}
			],
			"type" : "INTERNAL",
			"value" : "1"
		},
		{
			"name" : "protobuf_INSTALL",
			"properties" : 
			[
				{
					"name" : "HELPSTRING",
					"value" : "Install protobuf binaries and files"
				}
			],
			"type" : "BOOL",
			"value" : "ON"
		},
		{
			"name" : "protobuf_INSTALL_EXAMPLES",
			"properties" : 
			[
				{
					"name" : "HELPSTRING",
					"value" : "Install the examples folder"
				}
			],
			"type" : "BOOL",
			"value" : "OFF"
		},
		{
			"name" : "protobuf_IS_TOP_LEVEL",
			"properties" : 
			[
				{
					"name" : "HELPSTRING",
					"value" : "Value Computed by CMake"
				}
			],
			"type" : "STATIC",
			"value" : "OFF"
		},
		{
			"name" : "protobuf_JSONCPP_PROVIDER",
			"properties" : 
			[
				{
					"name" : "HELPSTRING",
					"value" : "Provider of jsoncpp library"
				},
				{
					"name" : "STRINGS",
					"value" : "module;package"
				}
			],
			"type" : "STRING",
			"value" : "module"
		},
		{
			"name" : "protobuf_MODULE_COMPATIBLE",
			"properties" : 
			[
				{
					"name" : "ADVANCED",
					"value" : "1"
				},
				{
					"name" : "HELPSTRING",
					"value" : "CMake built-in FindProtobuf.cmake module compatible"
				}
			],
			"type" : "BOOL",
			"value" : "OFF"
		},
		{
			"name" : "protobuf_MSVC_STATIC_RUNTIME",
			"properties" : 
			[
				{
					"name" : "HELPSTRING",
					"value" : "Link static runtime libraries"
				}
			],
			"type" : "BOOL",
			"value" : "OFF"
		},
		{
			"name" : "protobuf_SOURCE_DIR",
			"properties" : 
			[
				{
					"name" : "HELPSTRING",
					"value" : "Value Computed by CMake"
				}
			],
			"type" : "STATIC",
			"value" : "/home/aymanelotfi/Documents/millemiglia/build/_deps/protobuf-src"
		},
		{
			"name" : "protobuf_TEST_XML_OUTDIR",
			"properties" : 
			[
				{
					"name" : "HELPSTRING",
					"value" : "Output directory for XML logs from tests."
				}
			],
			"type" : "BOOL",
			"value" : "OFF"
		},
		{
			"name" : "protobuf_VERBOSE",
			"properties" : 
			[
				{
					"name" : "ADVANCED",
					"value" : "1"
				},
				{
					"name" : "HELPSTRING",
					"value" : "Enable for verbose output"
				}
			],
			"type" : "BOOL",
			"value" : "OFF"
		},
		{
			"name" : "protobuf_WITH_ZLIB",
			"properties" : 
			[
				{
					"name" : "HELPSTRING",
					"value" : "Build with zlib support"
				}
			],
			"type" : "BOOL",
			"value" : "ON"
		},
		{
			"name" : "random_distributions_LIB_DEPENDS",
			"properties" : 
			[
				{
					"name" : "HELPSTRING",
					"value" : "Dependencies for the target"
				}
			],
			"type" : "STATIC",
			"value" : "general;absl::random_internal_generate_real;general;absl::random_internal_distribution_caller;general;absl::random_internal_fast_uniform_bits;general;absl::random_internal_fastmath;general;absl::random_internal_iostream_state_saver;general;absl::random_internal_traits;general;absl::random_internal_uniform_helper;general;absl::random_internal_wide_multiply;general;absl::strings;"
		},
		{
			"name" : "random_internal_distribution_test_util_LIB_DEPENDS",
			"properties" : 
			[
				{
					"name" : "HELPSTRING",
					"value" : "Dependencies for the target"
				}
			],
			"type" : "STATIC",
			"value" : "general;absl::raw_logging_internal;general;absl::strings;general;absl::str_format;general;absl::span;"
		},
		{
			"name" : "random_internal_pool_urbg_LIB_DEPENDS",
			"properties" : 
			[
				{
					"name" : "HELPSTRING",
					"value" : "Dependencies for the target"
				}
			],
			"type" : "STATIC",
			"value" : "general;absl::base;general;absl::random_internal_randen;general;absl::random_internal_seed_material;general;absl::random_seed_gen_exception;general;absl::raw_logging_internal;general;absl::span;"
		},
		{
			"name" : "random_internal_randen_LIB_DEPENDS",
			"properties" : 
			[
				{
					"name" : "HELPSTRING",
					"value" : "Dependencies for the target"
				}
			],
			"type" : "STATIC",
			"value" : "general;absl::random_internal_platform;general;absl::random_internal_randen_hwaes;general;absl::random_internal_randen_slow;"
		},
		{
			"name" : "random_internal_randen_hwaes_LIB_DEPENDS",
			"properties" : 
			[
				{
					"name" : "HELPSTRING",
					"value" : "Dependencies for the target"
				}
			],
			"type" : "STATIC",
			"value" : "general;absl::random_internal_platform;general;absl::random_internal_randen_hwaes_impl;"
		},
		{
			"name" : "random_internal_randen_hwaes_impl_LIB_DEPENDS",
			"properties" : 
			[
				{
					"name" : "HELPSTRING",
					"value" : "Dependencies for the target"
				}
			],
			"type" : "STATIC",
			"value" : "general;absl::random_internal_platform;"
		},
		{
			"name" : "random_internal_randen_slow_LIB_DEPENDS",
			"properties" : 
			[
				{
					"name" : "HELPSTRING",
					"value" : "Dependencies for the target"
				}
			],
			"type" : "STATIC",
			"value" : "general;absl::random_internal_platform;"
		},
		{
			"name" : "random_internal_seed_material_LIB_DEPENDS",
			"properties" : 
			[
				{
					"name" : "HELPSTRING",
					"value" : "Dependencies for the target"
				}
			],
			"type" : "STATIC",
			"value" : "general;absl::optional;general;absl::raw_logging_internal;general;absl::span;general;absl::strings;"
		},
		{
			"name" : "random_seed_sequences_LIB_DEPENDS",
			"properties" : 
			[
				{
					"name" : "HELPSTRING",
					"value" : "Dependencies for the target"
				}
			],
			"type" : "STATIC",
			"value" : "general;absl::random_internal_pool_urbg;general;absl::random_internal_salted_seed_seq;general;absl::random_internal_seed_material;general;absl::random_seed_gen_exception;general;absl::span;"
		},
		{
			"name" : "raw_hash_set_LIB_DEPENDS",
			"properties" : 
			[
				{
					"name" : "HELPSTRING",
					"value" : "Dependencies for the target"
				}
			],
			"type" : "STATIC",
			"value" : "general;absl::bits;general;absl::hash;general;absl::hashtablez_sampler;general;absl::memory;general;absl::meta;general;absl::optional;general;absl::raw_logging_internal;general;absl::utility;"
		},
		{
			"name" : "raw_logging_internal_LIB_DEPENDS",
			"properties" : 
			[
				{
					"name" : "HELPSTRING",
					"value" : "Dependencies for the target"
				}
			],
			"type" : "STATIC",
			"value" : "general;absl::config;general;absl::core_headers;general;absl::log_severity;"
		},
		{
			"name" : "scoped_set_env_LIB_DEPENDS",
			"properties" : 
			[
				{
					"name" : "HELPSTRING",
					"value" : "Dependencies for the target"
				}
			],
			"type" : "STATIC",
			"value" : "general;absl::raw_logging_internal;"
		},
		{
			"name" : "spinlock_wait_LIB_DEPENDS",
			"properties" : 
			[
				{
					"name" : "HELPSTRING",
					"value" : "Dependencies for the target"
				}
			],
			"type" : "STATIC",
			"value" : "general;absl::base_internal;general;absl::core_headers;"
		},
		{
			"name" : "stacktrace_LIB_DEPENDS",
			"properties" : 
			[
				{
					"name" : "HELPSTRING",
					"value" : "Dependencies for the target"
				}
			],
			"type" : "STATIC",
			"value" : "general;absl::debugging_internal;general;absl::raw_logging_internal;"
		},
		{
			"name" : "status_LIB_DEPENDS",
			"properties" : 
			[
				{
					"name" : "HELPSTRING",
					"value" : "Dependencies for the target"
				}
			],
			"type" : "STATIC",
			"value" : "general;absl::cord;general;absl::optional;general;absl::raw_logging_internal;general;absl::span;general;absl::stacktrace;general;absl::strerror;general;absl::str_format;general;absl::strings;general;absl::symbolize;"
		},
		{
			"name" : "statusor_LIB_DEPENDS",
			"properties" : 
			[
				{
					"name" : "HELPSTRING",
					"value" : "Dependencies for the target"
				}
			],
			"type" : "STATIC",
			"value" : "general;absl::base;general;absl::has_ostream_operator;general;absl::raw_logging_internal;general;absl::status;general;absl::str_format;general;absl::strings;general;absl::utility;general;absl::variant;"
		},
		{
			"name" : "str_format_internal_LIB_DEPENDS",
			"properties" : 
			[
				{
					"name" : "HELPSTRING",
					"value" : "Dependencies for the target"
				}
			],
			"type" : "STATIC",
			"value" : "general;absl::strings;general;absl::utility;general;absl::int128;general;absl::span;"
		},
		{
			"name" : "string_view_LIB_DEPENDS",
			"properties" : 
			[
				{
					"name" : "HELPSTRING",
					"value" : "Dependencies for the target"
				}
			],
			"type" : "STATIC",
			"value" : "general;absl::base;general;absl::throw_delegate;"
		},
		{
			"name" : "strings_LIB_DEPENDS",
			"properties" : 
			[
				{
					"name" : "HELPSTRING",
					"value" : "Dependencies for the target"
				}
			],
			"type" : "STATIC",
			"value" : "general;absl::string_view;general;absl::strings_internal;general;absl::base;general;absl::charset;general;absl::int128;general;absl::raw_logging_internal;general;absl::throw_delegate;"
		},
		{
			"name" : "strings_internal_LIB_DEPENDS",
			"properties" : 
			[
				{
					"name" : "HELPSTRING",
					"value" : "Dependencies for the target"
				}
			],
			"type" : "STATIC",
			"value" : "general;absl::raw_logging_internal;"
		},
		{
			"name" : "symbolize_LIB_DEPENDS",
			"properties" : 
			[
				{
					"name" : "HELPSTRING",
					"value" : "Dependencies for the target"
				}
			],
			"type" : "STATIC",
			"value" : "general;absl::debugging_internal;general;absl::demangle_internal;general;absl::base;general;absl::malloc_internal;general;absl::raw_logging_internal;general;absl::strings;"
		},
		{
			"name" : "synchronization_LIB_DEPENDS",
			"properties" : 
			[
				{
					"name" : "HELPSTRING",
					"value" : "Dependencies for the target"
				}
			],
			"type" : "STATIC",
			"value" : "general;absl::graphcycles_internal;general;absl::kernel_timeout_internal;general;absl::base;general;absl::malloc_internal;general;absl::raw_logging_internal;general;absl::stacktrace;general;absl::symbolize;general;absl::time;"
		},
		{
			"name" : "throw_delegate_LIB_DEPENDS",
			"properties" : 
			[
				{
					"name" : "HELPSTRING",
					"value" : "Dependencies for the target"
				}
			],
			"type" : "STATIC",
			"value" : "general;absl::raw_logging_internal;"
		},
		{
			"name" : "time_LIB_DEPENDS",
			"properties" : 
			[
				{
					"name" : "HELPSTRING",
					"value" : "Dependencies for the target"
				}
			],
			"type" : "STATIC",
			"value" : "general;absl::base;general;absl::civil_time;general;absl::int128;general;absl::raw_logging_internal;general;absl::strings;general;absl::time_zone;"
		},
		{
			"name" : "utf8_range_BINARY_DIR",
			"properties" : 
			[
				{
					"name" : "HELPSTRING",
					"value" : "Value Computed by CMake"
				}
			],
			"type" : "STATIC",
			"value" : "/home/aymanelotfi/Documents/millemiglia/build/_deps/protobuf-build/third_party/utf8_range"
		},
		{
			"name" : "utf8_range_ENABLE_INSTALL",
			"properties" : 
			[
				{
					"name" : "HELPSTRING",
					"value" : "Configure installation"
				}
			],
			"type" : "BOOL",
			"value" : "ON"
		},
		{
			"name" : "utf8_range_ENABLE_TESTS",
			"properties" : 
			[
				{
					"name" : "HELPSTRING",
					"value" : "Build test suite"
				}
			],
			"type" : "BOOL",
			"value" : "OFF"
		},
		{
			"name" : "utf8_range_IS_TOP_LEVEL",
			"properties" : 
			[
				{
					"name" : "HELPSTRING",
					"value" : "Value Computed by CMake"
				}
			],
			"type" : "STATIC",
			"value" : "OFF"
		},
		{
			"name" : "utf8_range_SOURCE_DIR",
			"properties" : 
			[
				{
					"name" : "HELPSTRING",
					"value" : "Value Computed by CMake"
				}
			],
			"type" : "STATIC",
			"value" : "/home/aymanelotfi/Documents/millemiglia/build/_deps/protobuf-src/third_party/utf8_range"
		},
		{
			"name" : "utf8_validity_LIB_DEPENDS",
			"properties" : 
			[
				{
					"name" : "HELPSTRING",
					"value" : "Dependencies for the target"
				}
			],
			"type" : "STATIC",
			"value" : "general;absl::strings;"
		},
		{
			"name" : "vlog_config_internal_LIB_DEPENDS",
			"properties" : 
			[
				{
					"name" : "HELPSTRING",
					"value" : "Dependencies for the target"
				}
			],
			"type" : "STATIC",
			"value" : "general;absl::base;general;absl::log_internal_fnmatch;general;absl::memory;general;absl::strings;general;absl::synchronization;general;absl::optional;"
		}
	],
	"kind" : "cache",
	"version" : 
	{
		"major" : 2,
		"minor" : 0
	}
}
